libimagequant/_libimagequant.abi3.so
libimagequant/__init__.py
libimagequant-2.17.0.0.dist-info/LICENSE
libimagequant-2.17.0.0.dist-info/METADATA
libimagequant-2.17.0.0.dist-info/top_level.txt
libimagequant-2.17.0.0.dist-info/RECORD
libimagequant-2.17.0.0.dist-info/WHEEL
