Metadata-Version: 2.1
Name: libimagequant
Version: 2.17.0.0
Summary: Unofficial Python bindings for libimagequant
Home-page: https://github.com/RoadrunnerWMC/libimagequant-python
Author: RoadrunnerWMC, Kornel Lesiński
Author-email: roadrunnerwmc@gmail.com
License: UNKNOWN
Platform: UNKNOWN
Classifier: Programming Language :: C
Classifier: Programming Language :: Python :: 3.6
Classifier: Programming Language :: Python :: 3.7
Classifier: Programming Language :: Python :: 3.8
Classifier: Programming Language :: Python :: 3.9
Classifier: Programming Language :: Python :: 3.10
Classifier: Programming Language :: Python :: Implementation :: PyPy
Classifier: Topic :: Multimedia :: Graphics
Classifier: License :: OSI Approved :: GNU General Public License v3 or later (GPLv3+)
Requires-Python: >=3.6
License-File: LICENSE
